wsgi_server/__init__.py
wsgi_server/server.py
peleren-1.0.2.dist-info/LICENSE
peleren-1.0.2.dist-info/METADATA
peleren-1.0.2.dist-info/WHEEL
peleren-1.0.2.dist-info/entry_points.txt
peleren-1.0.2.dist-info/top_level.txt
peleren-1.0.2.dist-info/RECORD
