Metadata-Version: 2.1
Name: peleren
Version: 1.0.2
Summary: A simple WSGI server optimized for AI applications
Home-page: https://github.com/Marc-Arold/peleren
Author: Marc Arold ROSEMOND
Author-email: rosemondmarcarold@gmail.com
Classifier: Programming Language :: Python :: 3
Classifier: License :: OSI Approved :: MIT License
Classifier: Operating System :: OS Independent
Requires-Python: >=3.6
License-File: LICENSE
